bgsutils.py
bgsutils-0.1.2.dist-info/LICENSE
bgsutils-0.1.2.dist-info/METADATA
bgsutils-0.1.2.dist-info/WHEEL
bgsutils-0.1.2.dist-info/RECORD
