Metadata-Version: 2.1
Name: bgsutils
Version: 0.1.2
Summary: Be GeoSpatial public utils python tools
License: MIT
Author: José Beltrán
Author-email: 102664984+jose-begeospatial@users.noreply.github.com
Requires-Python: >=3.11,<4.0
Classifier: License :: OSI Approved :: MIT License
Classifier: Programming Language :: Python :: 3
Classifier: Programming Language :: Python :: 3.11
